jsonifable/__init__.py
jsonifable/jsonifable.py
jsonifable-0.1.0.dist-info/LICENSE
jsonifable-0.1.0.dist-info/METADATA
jsonifable-0.1.0.dist-info/WHEEL
jsonifable-0.1.0.dist-info/top_level.txt
jsonifable-0.1.0.dist-info/RECORD
